dappy/__init__.py
dappy/api.py
dappy/endpoint.py
dappy/exceptions.py
dappy/formatters.py
dappy/methods.py
dappy-3.0.3.dist-info/AUTHORS.rst
dappy-3.0.3.dist-info/LICENSE
dappy-3.0.3.dist-info/METADATA
dappy-3.0.3.dist-info/WHEEL
dappy-3.0.3.dist-info/top_level.txt
dappy-3.0.3.dist-info/RECORD
