Metadata-Version: 2.1
Name: dappy
Version: 3.0.3
Summary: Define API suites declaratively
Home-page: https://gitlab.com/heathercreech/dappy
Author: Heather Creech
Author-email: heatherannecreech@gmail.com
License: MIT license
Keywords: dappy
Platform: UNKNOWN
Classifier: Development Status :: 2 - Pre-Alpha
Classifier: Intended Audience :: Developers
Classifier: License :: OSI Approved :: MIT License
Classifier: Natural Language :: English
Classifier: Programming Language :: Python :: 3.5
Requires-Dist: requests (>=2.18.4)
